djangovue/__init__.py
djangovue/apps.py
djangovue/forms/__init__.py
djangovue/forms/widgets.py
djangovue/static/djangovue/djangovue.js
djangovue/static/djangovue/djangovue.js.map
djangovue/templatetags/__init__.py
djangovue/templatetags/djangovue.py
djangovue/vue.py
djangovue-0.0.12.dist-info/LICENSE
djangovue-0.0.12.dist-info/WHEEL
djangovue-0.0.12.dist-info/METADATA
djangovue-0.0.12.dist-info/RECORD
