Metadata-Version: 2.1
Name: djangovue
Version: 0.0.12
Summary: A set of helper tags and form widgets for making django and vue play nicely.
Home-page: https://gitlab.com/BradleyKirton/djangovue/
License: MIT
Keywords: django,vue
Author: Bradley Stuart Kirton
Author-email: bradleykirton@gmail.com
Requires-Python: >=3.6,<4.0
Classifier: Development Status :: 4 - Beta
Classifier: Environment :: Web Environment
Classifier: Framework :: Django
Classifier: Framework :: Django :: 2.1
Classifier: Intended Audience :: Developers
Classifier: License :: OSI Approved :: MIT License
Classifier: Operating System :: OS Independent
Classifier: Programming Language :: Python :: 3
Classifier: Programming Language :: Python :: 3.6
Classifier: Programming Language :: Python :: 3.7
Classifier: Programming Language :: Python :: 3.8
Classifier: Topic :: Software Development :: Libraries
Classifier: Topic :: Utilities
Requires-Dist: django (>=2.1,<3.0)
Project-URL: Repository, https://gitlab.com/BradleyKirton/djangovue/
